fpa.sv
module fpa(
    input logic [31:0] a,
    input logic [31:0] b,
    output logic [31:0] c 
);

logic sign_a;
logic [7:0] exponent_a;
logic [23:0] significand_a;

logic sign_b;
logic [7:0] exponent_b;
logic [23:0] significand_b;

logic [7:0] exponent_c;
logic [24:0] significand_c;

logic [7:0] diff;

integer i;

always_comb begin
    sign_a = a[31];
    exponent_a = a[30:23];
    significand_a = {1'b1, a[22:0]};

    sign_b = b[31];
    exponent_b = b[30:23];
    significand_b = {1'b1, b[22:0]};

    //make exponents equal
    if(exponent_b < exponent_a) begin
        diff = exponent_a - exponent_b;
        significand_b = significand_b >> diff;
        exponent_b = exponent_a;
    end
    else begin
        diff = exponent_b - exponent_a;
        significand_a = significand_a >> diff;
        exponent_a = exponent_b;
    end

    //add or subtract significands
    if(sign_a == sign_b) begin
        c[31] = sign_a;
        significand_c = significand_a + significand_b;
    end
    else begin
        if(significand_a <= significand_b) begin
            c[31] = sign_b;
            significand_c = significand_b - significand_a;
        end else begin
            c[31] = sign_a;
            significand_c = significand_a - significand_b;
        end
    end
    exponent_c = exponent_a;

    //account for offsets
    if(significand_c[24]) begin
        significand_c = significand_c >> 1;
        exponent_c = exponent_c + 1;
    end else begin

        //change this to a chain of if/else ?
        //might not be necessary (not comb)
        for(i = 0; i < 23; i = i + 1)begin
            if(significand_c[23] == 0)begin
                significand_c = significand_c << 1;
                exponent_c = exponent_c - 1;
            end
        end
    end
    c[30:23] = exponent_c;
    c[22:0] = significand_c[22:0];
end
endmodule

fpa_tb.sv
`timescale 1ns / 1ps

//`include "fpa.sv"

module fpa_tb;

    logic [31:0] a;
    logic [31:0] b;
    logic [31:0] c;

    int pass_count = 0;
    int fail_count = 0;

    fpa fpa (
        .a(a),
        .b(b),
        .c(c)
    );

    task run_test(logic [31:0] test_a, logic [31:0] test_b, logic [31:0] expected);
        begin
            a = test_a;
            b = test_b;
            #5; // quick wait for logic to settle
 
            if (c === expected) begin
                pass_count++;
                $display("a=%016b b=%016b | out=%016b | PASS", test_a, test_b, c);
            end 
            else begin
                fail_count++;
                $display("a=%016b b=%016b | out=%016b expected=%016b | FAIL", test_a, test_b, c, expected);
            end
        end
    endtask

    initial begin
        $dumpfile("waveform.vcd");
        $dumpvars(0, fpa_tb);

        a = 0; 
        b = 0;
        #5;

        run_test(32'h3F800000, 32'h3F800000, 32'h40000000); // 1.0 + 1.0 = 2.0
        run_test(32'h40000000, 32'hBF800000, 32'h3F800000); // 2.0 + (-1.0) = 1.0  (different signs, no cancellation to zero)
        run_test(32'h3FC00000, 32'h40200000, 32'h40800000); // 1.5 + 2.5 = 4.0
        run_test(32'h40400000, 32'h40800000, 32'h40E00000); // 3.0 + 4.0 = 7.0
        run_test(32'hC0400000, 32'h3F800000, 32'hC0000000); // -3.0 + 1.0 = -2.0
        run_test(32'h41000000, 32'h41000000, 32'h41800000); // 8.0 + 8.0 = 16.0 (forces the significand_c[24] carry-out normalize path)
        run_test(32'h3FA00000, 32'h3FA00000, 32'h40200000); // 1.25 + 1.25 = 2.5
        run_test(32'h49800000, 32'h49800000, 32'h4A000000); // 2^20 + 2^20 = 2^21 (large exponent alignment, no shift needed)// -1.0 + -1.0 = -2.0 (same sign, negative, exercises carry path w/ sign)
        run_test(32'hBF800000, 32'hBF800000, 32'hC0000000); // -1.0 + -1.0 = -2.0 (same sign, negative, exercises carry path w/ sign)
 
        // 1.0 + 2^-30 = 1.0 (exponent diff of 30 shifts significand_b fully to
        // zero before it can affect the sum -- truncation is "safe" here since
        // no bits of the final result depend on what got shifted out)
        run_test(32'h3F800000, 32'h30800000, 32'h3F800000);
 
        // Zero + zero -- KNOWN BUG: significand_a/b force an implicit leading 1
        // even when exponent==0 and mantissa==0, so this does NOT produce true
        // zero on the current DUT. Expected value here is the correct IEEE-754
        // result (0.0); this test is expected to FAIL until the zero-input
        // special case is added.
        run_test(32'h00000000, 32'h00000000, 32'h00000000);
 
        // 5.0 + (-5.0) = 0.0 -- KNOWN BUG: exact cancellation leaves
        // significand_c == 0, and the normalize loop decrements exponent_c
        // 23 times unconditionally with no zero-result check, corrupting the
        // exponent field. Expected value here is the correct IEEE-754 result
        // (0.0); this test is expected to FAIL until a zero-result check is
        // added before/after normalization.
        run_test(32'h40A00000, 32'hC0A00000, 32'h00000000);
 
        $display("Results: %0d passed, %0d failed (of %0d total)", pass_count, fail_count, pass_count + fail_count);

        $finish;
    end
 
endmodule

waveform.vcd
$date
	Mon Aug  3 01:15:51 2026
$end
$version
	Icarus Verilog
$end
$timescale
	1ps
$end
$scope module fpa_tb $end
$var wire 32 ! c [31:0] $end
$var reg 32 " a [31:0] $end
$var reg 32 # b [31:0] $end
$var integer 32 $ fail_count [31:0] $end
$var integer 32 % pass_count [31:0] $end
$scope module fpa $end
$var wire 32 & a [31:0] $end
$var wire 32 ' b [31:0] $end
$var reg 32 ( c [31:0] $end
$var reg 8 ) diff [7:0] $end
$var reg 8 * exponent_a [7:0] $end
$var reg 8 + exponent_b [7:0] $end
$var reg 8 , exponent_c [7:0] $end
$var reg 1 - sign_a $end
$var reg 1 . sign_b $end
$var reg 24 / significand_a [23:0] $end
$var reg 24 0 significand_b [23:0] $end
$var reg 25 1 significand_c [24:0] $end
$var integer 32 2 i [31:0] $end
$upscope $end
$scope task run_test $end
$var reg 32 3 expected [31:0] $end
$var reg 32 4 test_a [31:0] $end
$var reg 32 5 test_b [31:0] $end
$upscope $end
$upscope $end
$enddefinitions $end
#0
$dumpvars
bx 5
bx 4
bx 3
bx 2
b100000000000000000000000 1
b100000000000000000000000 0
b100000000000000000000000 /
0.
0-
b1 ,
b0 +
b0 *
b0 )
b100000000000000000000000 (
b0 '
b0 &
b0 %
b0 $
b0 #
b0 "
b100000000000000000000000 !
$end
#5000
b1000000000000000000000000000000 !
b1000000000000000000000000000000 (
b10000000 ,
b100000000000000000000000 1
b1111111 +
b1111111 *
b111111100000000000000000000000 #
b111111100000000000000000000000 '
b111111100000000000000000000000 "
b111111100000000000000000000000 &
b1000000000000000000000000000000 3
b111111100000000000000000000000 5
b111111100000000000000000000000 4
#10000
b111111100000000000000000000000 !
b111111100000000000000000000000 (
b1111111 ,
b10111 2
b100000000000000000000000 1
b10000000 +
b10000000000000000000000 0
b1 )
1.
b10000000 *
b10111111100000000000000000000000 #
b10111111100000000000000000000000 '
b1000000000000000000000000000000 "
b1000000000000000000000000000000 &
b111111100000000000000000000000 3
b10111111100000000000000000000000 5
b1000000000000000000000000000000 4
b1 %
#15000
b1000000100000000000000000000000 !
b1000000100000000000000000000000 (
b10000001 ,
b100000000000000000000000 1
b101000000000000000000000 0
0.
b11000000000000000000000 /
b10000000 *
b1000000001000000000000000000000 #
b1000000001000000000000000000000 '
b111111110000000000000000000000 "
b111111110000000000000000000000 &
b1000000100000000000000000000000 3
b1000000001000000000000000000000 5
b111111110000000000000000000000 4
b10 %
#20000
b1000000111000000000000000000000 !
b1000000111000000000000000000000 (
b10111 2
b111000000000000000000000 1
b10000001 *
b100000000000000000000000 0
b10000001 +
b11000000000000000000000 /
b1000000100000000000000000000000 #
b1000000100000000000000000000000 '
b1000000010000000000000000000000 "
b1000000010000000000000000000000 &
b1000000111000000000000000000000 3
b1000000100000000000000000000000 5
b1000000010000000000000000000000 4
b11 %
#25000
b10111 2
b10000000 ,
b100000000000000000000000 1
b11000000000000000000000000000000 !
b11000000000000000000000000000000 (
b10000000000000000000000 0
b10000000 +
b110000000000000000000000 /
b10000000 *
1-
b111111100000000000000000000000 #
b111111100000000000000000000000 '
b11000000010000000000000000000000 "
b11000000010000000000000000000000 &
b11000000000000000000000000000000 3
b111111100000000000000000000000 5
b11000000010000000000000000000000 4
b100 %
#30000
b10000011 ,
b100000000000000000000000 1
b1000001100000000000000000000000 !
b1000001100000000000000000000000 (
b0 )
b100000000000000000000000 0
b10000010 +
b100000000000000000000000 /
b10000010 *
0-
b1000001000000000000000000000000 #
b1000001000000000000000000000000 '
b1000001000000000000000000000000 "
b1000001000000000000000000000000 &
b1000001100000000000000000000000 3
b1000001000000000000000000000000 5
b1000001000000000000000000000000 4
b101 %
#35000
b1000000001000000000000000000000 !
b1000000001000000000000000000000 (
b10000000 ,
b101000000000000000000000 1
b101000000000000000000000 0
b1111111 +
b101000000000000000000000 /
b1111111 *
b111111101000000000000000000000 #
b111111101000000000000000000000 '
b111111101000000000000000000000 "
b111111101000000000000000000000 &
b1000000001000000000000000000000 3
b111111101000000000000000000000 5
b111111101000000000000000000000 4
b110 %
#40000
b1001010000000000000000000000000 !
b1001010000000000000000000000000 (
b10010100 ,
b100000000000000000000000 1
b100000000000000000000000 0
b10010011 +
b100000000000000000000000 /
b10010011 *
b1001001100000000000000000000000 #
b1001001100000000000000000000000 '
b1001001100000000000000000000000 "
b1001001100000000000000000000000 &
b1001010000000000000000000000000 3
b1001001100000000000000000000000 5
b1001001100000000000000000000000 4
b111 %
#45000
b10000000 ,
b100000000000000000000000 1
b11000000000000000000000000000000 !
b11000000000000000000000000000000 (
b1111111 +
1.
b1111111 *
1-
b10111111100000000000000000000000 #
b10111111100000000000000000000000 '
b10111111100000000000000000000000 "
b10111111100000000000000000000000 &
b11000000000000000000000000000000 3
b10111111100000000000000000000000 5
b10111111100000000000000000000000 4
b1000 %
#50000
b10111 2
b1111111 ,
b111111100000000000000000000000 !
b111111100000000000000000000000 (
b0 0
b11110 )
b1111111 +
0.
0-
b110000100000000000000000000000 #
b110000100000000000000000000000 '
b111111100000000000000000000000 "
b111111100000000000000000000000 &
b111111100000000000000000000000 3
b110000100000000000000000000000 5
b111111100000000000000000000000 4
b1001 %
#55000
b100000000000000000000000 !
b100000000000000000000000 (
b1 ,
b100000000000000000000000 1
b0 )
b100000000000000000000000 0
b0 +
b0 *
b0 #
b0 '
b0 "
b0 &
b0 3
b0 5
b0 4
b1010 %
#60000
b10111 2
b1101010 ,
b0 1
b10110101000000000000000000000000 !
b10110101000000000000000000000000 (
b101000000000000000000000 0
b10000001 +
1.
b101000000000000000000000 /
b10000001 *
b11000000101000000000000000000000 #
b11000000101000000000000000000000 '
b1000000101000000000000000000000 "
b1000000101000000000000000000000 &
b11000000101000000000000000000000 5
b1000000101000000000000000000000 4
b1 $
#65000
b10 $
