fpa.sv

//floating point adder that rounds by truncating


module fpa #(
parameter EXP = 8,
parameter MANT = 23
)(
    input logic [EXP+MANT:0] a,
    input logic [EXP+MANT:0] b,
    output logic [EXP+MANT:0] c 
);

logic sign_a;
logic [EXP-1:0] exponent_a;
logic [MANT:0] mantissa_a;

logic sign_b;
logic [EXP-1:0] exponent_b;
logic [MANT:0] mantissa_b;

logic [EXP-1:0] exponent_c;
logic [MANT+3:0] mantissa_c;

logic [EXP-1:0] diff;

integer i;

always_comb begin

    
    sign_a = a[EXP+MANT];
    exponent_a = a[EXP+MANT-1:MANT];
    

    sign_b = b[EXP+MANT];
    exponent_b = b[EXP+MANT-1:MANT];

    if(exponent_a == '0)begin
        mantissa_a = a[MANT-1:0];
        mantissa_b = {1'b1, b[MANT-1:0]};
    end
    else if
    (exponent_b == '0) begin
        mantissa_a = {1'b1, a[MANT-1:0]};
        mantissa_b = b[MANT-1:0];
    end
    else begin
        mantissa_a = {1'b1, a[MANT-1:0]};
        mantissa_b = {1'b1, b[MANT-1:0]};
    end
   
    
    //make exponents equal
    if(exponent_b < exponent_a) begin
        diff = exponent_a - exponent_b;
        mantissa_b = mantissa_b >> diff;
        exponent_b = exponent_a;
    end
    else begin
        diff = exponent_b - exponent_a;
        mantissa_a = mantissa_a >> diff;
        exponent_a = exponent_b;
    end

    //add or subtract mantissas
    if(sign_a == sign_b) begin
        c[EXP+MANT] = sign_a;
        mantissa_c = mantissa_a + mantissa_b;
    end
    else begin
        if(mantissa_a <= mantissa_b) begin
            c[EXP+MANT] = sign_b;
            mantissa_c = mantissa_b - mantissa_a;
        end else begin
            c[EXP+MANT] = sign_a;
            mantissa_c = mantissa_a - mantissa_b;
        end
    end
    exponent_c = exponent_a;

    if(mantissa_c == '0)begin
        mantissa_c = '0;
        exponent_c = '0;
        c[EXP+MANT] = 1'b0;
    end
    else begin
        //account for offsets
        if(mantissa_c[MANT+1]) begin
            mantissa_c = mantissa_c >> 1;
            exponent_c = exponent_c + 1;
        end else begin

            //normalization
            for(i = 0; i < MANT; i = i + 1)begin
                if(mantissa_c[MANT] == 0)begin
                    mantissa_c = mantissa_c << 1;
                    exponent_c = exponent_c - 1;
                end
            end
        end
    end
    c[EXP+MANT-1:MANT] = exponent_c;
    c[MANT-1:0] = mantissa_c[MANT-1:0];
    
end

endmodule

tb_fp16a.sv
`timescale 1ns / 1ps

//`include "fpa.sv"

module tb_fp6a;

    localparam int EXPONENT = 5;
    localparam int MANTISSA = 10;
    localparam int TOTAL = MANTISSA + EXPONENT;

    logic [TOTAL:0] a;
    logic [TOTAL:0] b;
    logic [TOTAL:0] c;

    fpa#(
        .MANT(MANTISSA),
        .EXP(EXPONENT)
    )  fpa (
        .a(a),
        .b(b),
        .c(c)
    );

    task run_test(logic [TOTAL:0] test_a, logic [TOTAL:0] test_b, logic [TOTAL:0] expected);
        begin
            a = test_a;
            b = test_b;
            #5; // quick wait for logic to settle
 
            if (c === expected) begin
                $display("a=%016b b=%016b out=%016b PASS", test_a, test_b, c);
            end 
            else begin
                $display("a=%016b b=%016b out=%016b expected=%016b FAIL", test_a, test_b, c, expected);
            end
        end
    endtask

    initial begin
        $dumpfile("waveform.vcd");
        $dumpvars(0, tb_fp6a);

        a = 0; 
        b = 0;
        #5;

        //Zero + zero
        run_test(16'b0000000000000000, 16'b0000000000000000, 16'b0000000000000000);

        //Zero + nonzero: 0+5.0 = 5.0
        run_test(16'b0000000000000000, 16'b0100010100000000, 16'b0100010100000000);

        //To have them cancel out: -3.0+3.0 = 0.0
        run_test(16'b1100001000000000, 16'b0100001000000000, 16'b0000000000000000);

        //Neg w/ same sign: -2.5+ -2.5 = -5.0
        run_test(16'b1100000100000000, 16'b1100000100000000, 16'b1100010100000000);

        //Forces right shift to normalize: 1.5+1.75 = 3.25
        run_test(16'b0011111000000000, 16'b0011111100000000, 16'b0100001010000000);

        //Forces left shift normalize and it almost cancels: 1.03125+ -1.0 = 0.03125
        run_test(16'b0011110000100000, 16'b1011110000000000, 16'b0010100000000000);

        //Very big difference in exponents: 1024.0+2^-10 = 1024.0
        run_test(16'b0110010000000000, 16'b0001010000000000, 16'b0110010000000000);

        //It has to shift the same amt as the mant: 32.0+0.03125 = 32.03125
        run_test(16'b0101000000000000, 16'b0010100000000000, 16'b0101000000000001);

        //Different signs, large magnitude cancellation: -100.0+100.0 = 0.0
        run_test(16'b1101011001000000, 16'b0101011001000000, 16'b0000000000000000);

        //Opposite signs but basic #s: 10.0+ -3.0 = 7.0
        run_test(16'b0100100100000000, 16'b1100001000000000, 16'b0100011100000000);

        //Smallest exp + smallest exp: 2^-14+2^-14 = 2^-13
        run_test(16'b0000010000000000, 16'b0000010000000000, 16'b0000100000000000);

        //Large magnitudes that are near top of the range: 30000.0+30000.0 = 60000.0
        run_test(16'b0111011101010011, 16'b0111011101010011, 16'b0111101101010011);

        //Doubling that requires a right shift to normalize: 6.0+6.0 = 12.0
        run_test(16'b0100011000000000, 16'b0100011000000000, 16'b0100101000000000);
        
        $finish;

    end
 
endmodule

waveform.vcd
$date
	Wed Aug  5 14:43:00 2026
$end
$version
	Icarus Verilog
$end
$timescale
	1ps
$end
$scope module tb_fp6a $end
$var wire 16 ! c [15:0] $end
$var reg 16 " a [15:0] $end
$var reg 16 # b [15:0] $end
$scope module fpa $end
$var wire 16 $ a [15:0] $end
$var wire 16 % b [15:0] $end
$var reg 16 & c [15:0] $end
$var reg 5 ' diff [4:0] $end
$var reg 5 ( exponent_a [4:0] $end
$var reg 5 ) exponent_b [4:0] $end
$var reg 5 * exponent_c [4:0] $end
$var reg 11 + mantissa_a [10:0] $end
$var reg 11 , mantissa_b [10:0] $end
$var reg 12 - mantissa_c [11:0] $end
$var reg 1 . sign_a $end
$var reg 1 / sign_b $end
$var integer 32 0 i [31:0] $end
$upscope $end
$scope task run_test $end
$var reg 16 1 expected [15:0] $end
$var reg 16 2 test_a [15:0] $end
$var reg 16 3 test_b [15:0] $end
$upscope $end
$upscope $end
$enddefinitions $end
#0
$dumpvars
bx 3
bx 2
bx 1
b1010 0
0/
0.
b10000000000 -
b10000000000 ,
b0 +
b0 *
b0 )
b0 (
b0 '
b0 &
b0 %
b0 $
b0 #
b0 "
b0 !
$end
#5000
b0 1
b0 3
b0 2
#10000
b100010100000000 !
b100010100000000 &
b1010 0
b10001 *
b10100000000 -
b10001 (
b10001 '
b10100000000 ,
b10001 )
b100010100000000 #
b100010100000000 %
b100010100000000 1
b100010100000000 3
#15000
b0 !
b0 &
b0 *
b0 -
b0 '
b11000000000 ,
b11000000000 +
b10000 )
b10000 (
1.
b100001000000000 #
b100001000000000 %
b1100001000000000 "
b1100001000000000 $
b0 1
b100001000000000 3
b1100001000000000 2
#20000
b10001 *
b10100000000 -
b1100010100000000 !
b1100010100000000 &
b10100000000 ,
b10100000000 +
1/
b1100000100000000 #
b1100000100000000 %
b1100000100000000 "
b1100000100000000 $
b1100010100000000 1
b1100000100000000 3
b1100000100000000 2
#25000
b10000 *
b11010000000 -
b100001010000000 !
b100001010000000 &
b11100000000 ,
b11000000000 +
b1111 )
0/
b1111 (
0.
b11111100000000 #
b11111100000000 %
b11111000000000 "
b11111000000000 $
b100001010000000 1
b11111100000000 3
b11111000000000 2
#30000
b10100000000000 !
b10100000000000 &
b1010 0
b1010 *
b10000000000 -
b10000000000 ,
b10000100000 +
1/
b1011110000000000 #
b1011110000000000 %
b11110000100000 "
b11110000100000 $
b10100000000000 1
b1011110000000000 3
b11110000100000 2
#35000
b110010000000000 !
b110010000000000 &
b1010 0
b11001 *
b0 ,
b10100 '
b10000000000 +
b11001 )
0/
b11001 (
b1010000000000 #
b1010000000000 %
b110010000000000 "
b110010000000000 $
b110010000000000 1
b1010000000000 3
b110010000000000 2
#40000
b101000000000001 !
b101000000000001 &
b1010 0
b10100 *
b10000000001 -
b1010 '
b1 ,
b10100 )
b10100 (
b10100000000000 #
b10100000000000 %
b101000000000000 "
b101000000000000 $
b101000000000001 1
b10100000000000 3
b101000000000000 2
#45000
b0 !
b0 &
b0 *
b0 -
b0 '
b11001000000 ,
b11001000000 +
b10101 )
b10101 (
1.
b101011001000000 #
b101011001000000 %
b1101011001000000 "
b1101011001000000 $
b0 1
b101011001000000 3
b1101011001000000 2
#50000
b100011100000000 !
b100011100000000 &
b1010 0
b10001 *
b11100000000 -
b10 '
b110000000 ,
b10100000000 +
b10010 )
1/
b10010 (
0.
b1100001000000000 #
b1100001000000000 %
b100100100000000 "
b100100100000000 $
b100011100000000 1
b1100001000000000 3
b100100100000000 2
#55000
b100000000000 !
b100000000000 &
b10 *
b10000000000 -
b0 '
b10000000000 ,
b10000000000 +
b1 )
0/
b1 (
b10000000000 #
b10000000000 %
b10000000000 "
b10000000000 $
b100000000000 1
b10000000000 3
b10000000000 2
#60000
b111101101010011 !
b111101101010011 &
b11110 *
b11101010011 -
b11101010011 ,
b11101010011 +
b11101 )
b11101 (
b111011101010011 #
b111011101010011 %
b111011101010011 "
b111011101010011 $
b111101101010011 1
b111011101010011 3
b111011101010011 2
#65000
b100101000000000 !
b100101000000000 &
b10010 *
b11000000000 -
b11000000000 ,
b11000000000 +
b10001 )
b10001 (
b100011000000000 #
b100011000000000 %
b100011000000000 "
b100011000000000 $
b100101000000000 1
b100011000000000 3
b100011000000000 2
