fpa_pipe.sv
module fpa_pipe #(

    parameter EXP = 5, // FP32: 8; FP16: 5; BF16: 8
    parameter MANT = 10 // FP32: 23; FP16: 10; BF16: 7

)(
    input  logic clk,
    input  logic [EXP+MANT:0] a,
    input  logic [EXP+MANT:0] b,
    output logic [EXP+MANT:0] c 
);

    logic sign_a;
    logic [EXP-1:0] exponent_a;
    logic [MANT:0] mantissa_a;

    logic sign_b;
    logic [EXP-1:0] exponent_b;
    logic [MANT:0] mantissa_b;

    logic sign_c;
    logic [EXP-1:0] exponent_c;
    logic [MANT+1:0] mantissa_c;

    logic [EXP-1:0] diff;

    integer i;

    always_ff @(posedge clk) begin
        sign_a <= a[EXP+MANT];
        exponent_a <= a[EXP+MANT-1:MANT];

        sign_b <= b[EXP+MANT];
        exponent_b <= b[EXP+MANT-1:MANT];

        //Just an idea i was working with to make it not output to each variable multiple 
        //times in one clk to work w pipelining (and you would comment out the block below)
        //it fixed a few test cases
        mantissa_a <= (exponent_a == '0) ? a[MANT-1:0] : {1'b1, a[MANT-1:0]};
        mantissa_b <= (exponent_b == '0) ? b[MANT-1:0] : {1'b1, b[MANT-1:0]};
    end

    // always_ff @(posedge clk) begin

    //     if(exponent_a == '0)begin
    //         mantissa_a <= a[MANT-1:0];
    //         mantissa_b <= {1'b1, b[MANT-1:0]};
    //     end
    //     else if (exponent_b == '0) begin
    //         mantissa_a <= {1'b1, a[MANT-1:0]};
    //         mantissa_b <= b[MANT-1:0];
    //     end
    //     else begin
    //         mantissa_a <= {1'b1, a[MANT-1:0]};
    //         mantissa_b <= {1'b1, b[MANT-1:0]};
    //     end
    // end

    always_ff @(posedge clk) begin
    
        //make exponents equal
        if (exponent_b < exponent_a) begin
            diff = exponent_a - exponent_b;
            mantissa_b <= mantissa_b >> diff;
            exponent_b <= exponent_a;
        end
        else begin
            diff = exponent_b - exponent_a;
            mantissa_a <= mantissa_a >> diff;
            exponent_a <= exponent_b;
        end
    end

    //I added bc multiple blocks can't output to sign_c
    logic sign_sum;
    logic [EXP-1:0] exponent_sum;
    logic [MANT+1:0] mantissa_sum;

    always_ff @(posedge clk) begin
        exponent_sum <= exponent_a;

        if (sign_a == sign_b) begin
            sign_sum <= sign_a;
            mantissa_sum <= mantissa_a + mantissa_b;
        end
        else begin
            if (mantissa_a <= mantissa_b) begin
                sign_sum <= sign_b;
                mantissa_sum <= mantissa_b - mantissa_a;
            end 
            else begin
                sign_sum <= sign_a;
                mantissa_sum <= mantissa_a - mantissa_b;
            end
        end
    end

    always_ff @(posedge clk) begin

        if (mantissa_sum == '0) begin
            mantissa_c <= '0;
            exponent_c <= '0;
            sign_c <= 1'b0;
        end
        //If needs to be normalized
        else if (mantissa_sum[MANT+1]) begin
            mantissa_c <= mantissa_sum >> 1;
            exponent_c <= exponent_sum + 1;
            sign_c <= sign_sum;
        end
        //If its already normalized
        else if (mantissa_sum[MANT]) begin
            mantissa_c <= mantissa_sum;
            exponent_c <= exponent_sum;
            sign_c <= sign_sum;
        end
        else begin
            for (i = 0; i < MANT; i = i + 1) begin
                if (mantissa_sum[MANT] == 0) begin
                    mantissa_c <= mantissa_sum << 1;
                    exponent_c <= exponent_sum - 1;
                end
            end
            sign_c <= sign_sum;
        end
    end

    //I added it for sign bc i had to add a sign_c
    assign c[EXP+MANT] = sign_c;
    assign c[EXP+MANT-1:MANT] = exponent_c;
    assign c[MANT-1:0] = mantissa_c[MANT-1:0];

endmodule

tb_fp32.sv
module tb_fp32;

    localparam int MANTISSA = 23;
    localparam int EXPONENT = 8;
    localparam int TOTAL = MANTISSA + EXPONENT;

    logic clk;
    logic [31:0] a;
    logic [31:0] b;
    logic [31:0] c;

    fpa_pipe #(
        .MANT(MANTISSA),
        .EXP(EXPONENT)
    ) dut (
        .clk(clk),
        .a(a),
        .b(b),
        .c(c)
    );

    initial clk = 0;
    always #5 clk = ~clk;

    task run_test(logic [TOTAL:0] test_a, logic [TOTAL:0] test_b, logic [TOTAL:0] expected);
        begin
            a = test_a;
            b = test_b;
            
            // Note to self: repeat as many always_ff are in pipeline
            @(posedge clk);
            #1;
            @(posedge clk);
            #1;
            @(posedge clk);
            #1;
            @(posedge clk);
            #1;
            @(posedge clk);
            #1;
 
            if (c === expected) begin
                $display("a=%016b b=%016b out=%016b PASS", test_a, test_b, c);
            end 
            else begin
                $display("a=%016b b=%016b out=%016b expected=%016b FAIL", test_a, test_b, c, expected);
            end
        end
    endtask

    initial begin
        $dumpfile("waveform.vcd");
        $dumpvars(0, tb_fp32);

        a = 0; 
        b = 0;
        @(posedge clk); // Wait for clk edge
        #1; // Add small delay

        //TEST 1: Basic functionality
        run_test(32'h40000000, 32'h40400000, 32'h40A00000);

        //TEST 2: positive plus zero
        run_test(32'h40900000, 32'h00000000, 32'h40900000);

        //TEST 3: negative plus zero
        run_test(32'hC0900000, 32'h00000000, 32'hC0900000);

        //TEST 4: positive plus negative (positive is greater)
        run_test(32'h40A00000, 32'hC0000000, 32'h40400000);

        //TEST 5: positive plus negative (negative is greater)
        run_test(32'h40000000, 32'hC0A00000, 32'hC0400000);

        //TEST 6: zero result
        run_test(32'h40C80000, 32'hC0C80000, 32'h00000000);

        //TEST 7: zero plus zero
        run_test(32'h00000000, 32'h00000000, 32'h00000000);

        //TEST 8: equal exponents
        run_test(32'h3FC00000, 32'h3FA00000, 32'h40300000);

        //TEST 9: large and small exponent
        run_test(32'h3F800000, 32'h30800000, 32'h3F800000);

        //TEST 10: truncation
        run_test(32'h3F800000, 32'h3EFFFFFF, 32'h3FBFFFFF);
        
        $finish;

    end

    // initial begin
    //     //TEST 1: Basic functionality
    //     a = 32'h40000000; //3.0
    //     b = 32'h40400000; //2.0

    //     if(c == 32'h40A00000) begin
    //         $display("TEST 1 PASSED");
    //     end
    //     else begin
    //         $display("TEST 1 FAILED");
    //     end

    //     //TEST 2: positive plus zero
    //     #10
    //     a = 32'h40900000; //4.5
    //     b = 32'h00000000; //0
    //     #10
    //     if(c == 32'h40900000) begin
    //         $display("TEST 2 PASSED");
    //     end
    //     else begin
    //         $display("TEST 2 FAILED");
    //     end
    //     //TEST 3: negative plus zero
    //     #10
    //     a = 32'hC0900000; //-4.5
    //     b = 32'h00000000; //0
    //     #10
    //     if(c == 32'hC0900000) begin
    //         $display("TEST 3 PASSED");
    //     end
    //     else begin
    //         $display("TEST 3 FAILED");
    //     end
    //     //TEST 4: positive plus negative (positive is greater)
    //     #10
    //     a = 32'h40A00000; //5.0
    //     b = 32'hC0000000; //-2.0
    //     #10
    //     if(c == 32'h40400000) begin
    //         $display("TEST 4 PASSED");
    //     end
    //     else begin
    //         $display("TEST 4 FAILED");
    //     end
    //     //TEST 5: positive plus negative (negative is greater)
    //     #10
    //     a = 32'h40000000; //2.0
    //     b = 32'hC0A00000; //-5.0
    //     #10
    //     if(c == 32'hC0400000) begin
    //         $display("TEST 5 PASSED");
    //     end
    //     else begin
    //         $display("TEST 5 FAILED");
    //     end
    //     //TEST 6: zero result
    //     #10
    //     a = 32'h40C80000; //6.25
    //     b = 32'hC0C80000; //-6.25
    //     #10
    //     if(c == 32'h0) begin
    //         $display("TEST 6 PASSED");
    //     end
    //     else begin
    //         $display("TEST 6 FAILED");
    //     end
    //     //TEST 7: zero plus zero
    //     #10
    //     a = 32'h0; //0
    //     b = 32'h0; //0
    //     #10
    //     if(c == 32'h0) begin
    //         $display("TEST 7 PASSED");
    //     end
    //     else begin
    //         $display("TEST 7 FAILED");
    //     end
    //     //TEST 8: equal exponents
    //     #10
    //     a = 32'h3FC00000; //1.5
    //     b = 32'h3FA00000; //1.25
    //     #10
    //     if(c == 32'h40300000) begin
    //         $display("TEST 8 PASSED");
    //     end
    //     else begin
    //         $display("TEST 8 FAILED");
    //     end
    //     //TEST 9: large and small exponent
    //     #10
    //     a = 32'h3F800000; //1.0
    //     b = 32'h30800000; //2^-30
    //     #10
    //     if(c == 32'h3F800000) begin
    //         $display("TEST 9 PASSED");
    //     end
    //     else begin
    //         $display("TEST 9 FAILED");
    //     end
    //     //TEST 10: truncation
    //     #10
    //     a = 32'h3F800000; //1.0
    //     b = 32'h3EFFFFFF; //0.49
    //     #10
    //     if(c == 32'h3FBFFFFF) begin
    //         $display("TEST 10 PASSED");
    //     end
    //     else begin
    //         $display("TEST 10 FAILED");
    //     end
    //     $finish;
    // end

endmodule

waveform.vcd
$date
	Wed Aug  5 18:14:38 2026
$end
$version
	Icarus Verilog
$end
$timescale
	1s
$end
$scope module tb_fp32 $end
$var wire 32 ! c [31:0] $end
$var reg 32 " a [31:0] $end
$var reg 32 # b [31:0] $end
$var reg 1 $ clk $end
$scope module dut $end
$var wire 32 % a [31:0] $end
$var wire 32 & b [31:0] $end
$var wire 1 $ clk $end
$var wire 32 ' c [31:0] $end
$var reg 8 ( diff [7:0] $end
$var reg 8 ) exponent_a [7:0] $end
$var reg 8 * exponent_b [7:0] $end
$var reg 8 + exponent_c [7:0] $end
$var reg 8 , exponent_sum [7:0] $end
$var reg 24 - mantissa_a [23:0] $end
$var reg 24 . mantissa_b [23:0] $end
$var reg 25 / mantissa_c [24:0] $end
$var reg 25 0 mantissa_sum [24:0] $end
$var reg 1 1 sign_a $end
$var reg 1 2 sign_b $end
$var reg 1 3 sign_c $end
$var reg 1 4 sign_sum $end
$var integer 32 5 i [31:0] $end
$upscope $end
$scope task run_test $end
$var reg 32 6 expected [31:0] $end
$var reg 32 7 test_a [31:0] $end
$var reg 32 8 test_b [31:0] $end
$upscope $end
$upscope $end
$enddefinitions $end
#0
$dumpvars
bx 8
bx 7
bx 6
bx 5
x4
x3
x2
x1
bx 0
bx /
bx .
bx -
bx ,
bx +
bx *
bx )
bx (
bx '
b0 &
b0 %
0$
b0 #
b0 "
bx !
$end
#5
bx00000000000000000000000 .
bx00000000000000000000000 -
b0 *
02
b0 )
01
b10111 5
1$
#6
b1000000010000000000000000000000 #
b1000000010000000000000000000000 &
b1000000000000000000000000000000 "
b1000000000000000000000000000000 %
b1000000101000000000000000000000 6
b1000000010000000000000000000000 8
b1000000000000000000000000000000 7
#10
0$
#15
04
b0 ,
b10000000000000000000000 .
bx00000000000000000000000 -
b10000000 *
b0 )
b10111 5
b0 (
1$
#20
0$
#25
b110000000000000000000000 .
b10000000 )
b0 -
b0xxxxxxxxxxxxxxxxxxxxxxxxxxxxxxx !
b0xxxxxxxxxxxxxxxxxxxxxxxxxxxxxxx '
03
b10000000 (
b10111 5
1$
#30
0$
#35
b110000000000000000000000 0
b10000000 ,
b0 -
b10111 5
b0 (
1$
#40
0$
#45
b100000000000000000000000 -
b1000000010000000000000000000000 !
b1000000010000000000000000000000 '
b10000000 +
b110000000000000000000000 /
1$
#50
0$
#55
b1010000000000000000000000 0
1$
#56
b0 #
b0 &
b1000000100100000000000000000000 "
b1000000100100000000000000000000 %
b1000000100100000000000000000000 6
b0 8
b1000000100100000000000000000000 7
#60
0$
#65
b100000000000000000000000 .
b100100000000000000000000 -
b0 *
b10000001 )
b1000000101000000000000000000000 !
b1000000101000000000000000000000 '
b10000001 +
b101000000000000000000000 /
1$
#70
0$
#75
b1000100000000000000000000 0
b10000001 ,
b10000001 *
b0 .
b10000001 (
1$
#80
0$
#85
b100000000000000000000000 .
b0 *
b100100000000000000000000 0
b1000001000010000000000000000000 !
b1000001000010000000000000000000 '
b10000010 +
b100010000000000000000000 /
b0 (
1$
#90
0$
#95
b1000000100100000000000000000000 !
b1000000100100000000000000000000 '
b10000001 +
b100100000000000000000000 /
b1000100000000000000000000 0
b10000001 *
b0 .
b10000001 (
1$
#100
0$
#105
b100000000000000000000000 .
b0 *
b100100000000000000000000 0
b1000001000010000000000000000000 !
b1000001000010000000000000000000 '
b10000010 +
b100010000000000000000000 /
b0 (
1$
#106
b11000000100100000000000000000000 "
b11000000100100000000000000000000 %
b11000000100100000000000000000000 6
b11000000100100000000000000000000 7
#110
0$
#115
b1000000100100000000000000000000 !
b1000000100100000000000000000000 '
b10000001 +
b100100000000000000000000 /
b1000100000000000000000000 0
b10000001 *
b0 .
11
b10000001 (
1$
#120
0$
#125
b100000000000000000000000 .
b0 *
b100100000000000000000000 0
14
b1000001000010000000000000000000 !
b1000001000010000000000000000000 '
b10000010 +
b100010000000000000000000 /
b0 (
1$
#130
0$
#135
13
b11000000100100000000000000000000 !
b11000000100100000000000000000000 '
b10000001 +
b100100000000000000000000 /
b100000000000000000000 0
b10000001 *
b0 .
b10000001 (
1$
#140
0$
#145
b100000000000000000000000 .
b0 *
b100100000000000000000000 0
b11000000001000000000000000000000 !
b11000000001000000000000000000000 '
b10000000 +
b1000000000000000000000 /
b0 (
b10111 5
1$
#150
0$
#155
b11000000100100000000000000000000 !
b11000000100100000000000000000000 '
b10000001 +
b100100000000000000000000 /
b100000000000000000000 0
b10000001 *
b0 .
b10000001 (
1$
#156
b11000000000000000000000000000000 #
b11000000000000000000000000000000 &
b1000000101000000000000000000000 "
b1000000101000000000000000000000 %
b1000000010000000000000000000000 6
b11000000000000000000000000000000 8
b1000000101000000000000000000000 7
#160
0$
#165
b100000000000000000000000 .
b101000000000000000000000 -
b10000000 *
12
01
b100100000000000000000000 0
b11000000001000000000000000000000 !
b11000000001000000000000000000000 '
b10000000 +
b1000000000000000000000 /
b0 (
b10111 5
1$
#170
0$
#175
b11000000100100000000000000000000 !
b11000000100100000000000000000000 '
b10000001 +
b100100000000000000000000 /
b1000000000000000000000 0
04
b10000001 *
b10000000000000000000000 .
b1 (
1$
#180
0$
#185
b100000000000000000000000 .
b10000000 *
b11000000000000000000000 0
03
b1000000010000000000000000000000 !
b1000000010000000000000000000000 '
b10000000 +
b10000000000000000000000 /
b0 (
b10111 5
1$
#190
0$
#195
b110000000000000000000000 /
b1000000000000000000000 0
b10000001 *
b10000000000000000000000 .
b10111 5
b1 (
1$
#200
0$
#205
b100000000000000000000000 .
b10000000 *
b11000000000000000000000 0
b10000000000000000000000 /
b0 (
b10111 5
1$
#206
b11000000101000000000000000000000 #
b11000000101000000000000000000000 &
b1000000000000000000000000000000 "
b1000000000000000000000000000000 %
b11000000010000000000000000000000 6
b11000000101000000000000000000000 8
b1000000000000000000000000000000 7
#210
0$
#215
b110000000000000000000000 /
b1000000000000000000000 0
b10000000000000000000000 .
b100000000000000000000000 -
b10000001 *
b10000000 )
b10111 5
b1 (
1$
#220
0$
#225
b101000000000000000000000 .
b10000000 )
b100000000000000000000000 -
b10000000000000000000000 0
b10000000 ,
b10000000000000000000000 /
b10111 5
1$
#230
0$
#235
b111111100000000000000000000000 !
b111111100000000000000000000000 '
b1111111 +
b100000000000000000000000 /
b1000000000000000000000 0
14
b10000001 )
b10000000000000000000000 -
b10111 5
1$
#240
0$
#245
b100000000000000000000000 -
b10000000 )
b11000000000000000000000 0
b10000001 ,
b10111111110000000000000000000000 !
b10111111110000000000000000000000 '
13
b10000000000000000000000 /
b0 (
b10111 5
1$
#250
0$
#255
b11000000010000000000000000000000 !
b11000000010000000000000000000000 '
b10000000 +
b110000000000000000000000 /
b1000000000000000000000 0
b10000000 ,
b10000001 )
b10000000000000000000000 -
b10111 5
b1 (
1$
#256
b11000000110010000000000000000000 #
b11000000110010000000000000000000 &
b1000000110010000000000000000000 "
b1000000110010000000000000000000 %
b0 6
b11000000110010000000000000000000 8
b1000000110010000000000000000000 7
#260
0$
#265
b110010000000000000000000 .
b110010000000000000000000 -
b11000000000000000000000 0
b10000001 ,
b10111111110000000000000000000000 !
b10111111110000000000000000000000 '
b1111111 +
b10000000000000000000000 /
b0 (
b10111 5
1$
#270
0$
#275
b11000000010000000000000000000000 !
b11000000010000000000000000000000 '
b10000000 +
b110000000000000000000000 /
b0 0
b10111 5
1$
#280
0$
#285
03
b0 !
b0 '
b0 +
b0 /
1$
#290
0$
#295
1$
#300
0$
#305
1$
#306
b0 #
b0 &
b0 "
b0 %
b0 8
b0 7
#310
0$
#315
b100000000000000000000000 .
b110010000000000000000000 -
b0 *
02
b10000001 )
1$
#320
0$
#325
b100000000000000000000000 -
b0 )
b0 *
b0 .
b1010010000000000000000000 0
04
b10000001 (
1$
#330
0$
#335
b1000001001001000000000000000000 !
b1000001001001000000000000000000 '
b10000010 +
b101001000000000000000000 /
b100000000000000000000000 0
b0 ,
b100000000000000000000000 -
b0 (
1$
#340
0$
#345
b0 -
b0 !
b0 '
b0 +
b100000000000000000000000 /
1$
#350
0$
#355
b0 0
1$
#356
b111111101000000000000000000000 #
b111111101000000000000000000000 &
b111111110000000000000000000000 "
b111111110000000000000000000000 %
b1000000001100000000000000000000 6
b111111101000000000000000000000 8
b111111110000000000000000000000 7
#360
0$
#365
b1000000000000000000000 .
b10000000000000000000000 -
b1111111 *
b1111111 )
b0 /
1$
#370
0$
#375
b11000000000000000000000 0
b1111111 ,
b101000000000000000000000 .
b10000000000000000000000 -
1$
#380
0$
#385
b110000000000000000000000 -
b111000000000000000000000 0
b111111010000000000000000000000 !
b111111010000000000000000000000 '
b1111110 +
b110000000000000000000000 /
b10111 5
1$
#390
0$
#395
b111111111000000000000000000000 !
b111111111000000000000000000000 '
b1111111 +
b111000000000000000000000 /
b1011000000000000000000000 0
1$
#400
0$
#405
b1000000001100000000000000000000 !
b1000000001100000000000000000000 '
b10000000 +
b101100000000000000000000 /
1$
#406
b110000100000000000000000000000 #
b110000100000000000000000000000 &
b111111100000000000000000000000 "
b111111100000000000000000000000 %
b111111100000000000000000000000 6
b110000100000000000000000000000 8
b111111100000000000000000000000 7
#410
0$
#415
b100000000000000000000000 .
b110000000000000000000000 -
b1100001 *
1$
#420
0$
#425
b100000000000000000000000 -
b1100001 *
b100000000000000000000000 .
b1010000000000000000000000 0
b11110 (
1$
#430
0$
#435
b1000000001000000000000000000000 !
b1000000001000000000000000000000 '
b101000000000000000000000 /
b1000000000000000000000000 0
b1111111 *
b0 .
1$
#440
0$
#445
b1000000000000000000000000000000 !
b1000000000000000000000000000000 '
b100000000000000000000000 .
b1100001 *
b100000000000000000000000 0
b100000000000000000000000 /
b0 (
1$
#450
0$
#455
b111111100000000000000000000000 !
b111111100000000000000000000000 '
b1111111 +
b1000000000000000000000000 0
b1111111 *
b0 .
b11110 (
1$
#456
b111110111111111111111111111111 #
b111110111111111111111111111111 &
b111111101111111111111111111111 6
b111110111111111111111111111111 8
#460
0$
#465
b111111111111111111111111 .
b1111101 *
b100000000000000000000000 0
b1000000000000000000000000000000 !
b1000000000000000000000000000000 '
b10000000 +
b0 (
1$
#470
0$
#475
b111111100000000000000000000000 !
b111111100000000000000000000000 '
b1111111 +
b1011111111111111111111111 0
b1111111 *
b1111111111111111111111 .
b10 (
1$
#480
0$
#485
b111111111111111111111111 .
b1111101 *
b101111111111111111111111 0
b1000000001111111111111111111111 !
b1000000001111111111111111111111 '
b10000000 +
b101111111111111111111111 /
b0 (
1$
#490
0$
#495
b111111101111111111111111111111 !
b111111101111111111111111111111 '
b1111111 +
b1011111111111111111111111 0
b1111111 *
b1111111111111111111111 .
b10 (
1$
#500
0$
#505
b111111111111111111111111 .
b1111101 *
b101111111111111111111111 0
b1000000001111111111111111111111 !
b1000000001111111111111111111111 '
b10000000 +
b0 (
1$
